setup.cfg
setup.py
enecodhutils/__init__.py
enecodhutils.egg-info/PKG-INFO
enecodhutils.egg-info/SOURCES.txt
enecodhutils.egg-info/dependency_links.txt
enecodhutils.egg-info/requires.txt
enecodhutils.egg-info/top_level.txt
enecodhutils/database/__init__.py
enecodhutils/database/dh_mssql.py
enecodhutils/database/dh_mysql.py
enecodhutils/mail/__init__.py
enecodhutils/mail/outlook.py
enecodhutils/pipeline/__init__.py
enecodhutils/pipeline/dh_kafka.py
enecodhutils/validations/__init__.py
enecodhutils/validations/dh_at.py