Metadata-Version: 1.0
Name: enecodhutils
Version: 2.4.6
Summary: A python package containing all the boiler plate code for Eneco-datahub utils.
Home-page: UNKNOWN
Author: Dharmateja Yarlagadda
Author-email: dharmateja.yarlagadda@eneco.com
License: MIT
Platform: UNKNOWN
